core/__init__.py
core/fallback.py
core/keys.py
core/manager.py
core/models.py
core/pricing.py
core/router.py
core/schema.py
core/storage.py
dashboard/__init__.py
dashboard/__main__.py
dashboard/server.py
dashboard/templates/index.html
dashboard/templates/request_detail.html
llm_usage/__init__.py
llm_usage/llm.py
providers/__init__.py
providers/gemini_provider.py
providers/openai_provider.py
utils/llm-models.py
llm_usage-0.1.4.dist-info/METADATA
llm_usage-0.1.4.dist-info/WHEEL
llm_usage-0.1.4.dist-info/entry_points.txt
llm_usage-0.1.4.dist-info/top_level.txt
llm_usage-0.1.4.dist-info/RECORD
