Metadata-Version: 2.4
Name: llm-usage
Version: 0.1.4
Summary: LLM usage tracker with cost/latency logging, fallback, and a web dashboard
Author-email: Your Name <you@example.com>
License: MIT
Project-URL: homepage, https://github.com/your/repo
Requires-Python: >=3.10
Requires-Dist: openai>=1.100.0
Requires-Dist: google-genai>=1.31.0
Requires-Dist: fastapi>=0.112.0
Requires-Dist: uvicorn>=0.30.0
Requires-Dist: jinja2>=3.1.4
Requires-Dist: python-dotenv>=1.0.1
